pyadaptivecards/__init__.py
pyadaptivecards/abstract_components.py
pyadaptivecards/actions.py
pyadaptivecards/card.py
pyadaptivecards/components.py
pyadaptivecards/container.py
pyadaptivecards/inputs.py
pyadaptivecards/options.py
pyadaptivecards/utils.py
pyadaptivecards-0.1.0.dist-info/AUTHORS.rst
pyadaptivecards-0.1.0.dist-info/LICENSE
pyadaptivecards-0.1.0.dist-info/METADATA
pyadaptivecards-0.1.0.dist-info/WHEEL
pyadaptivecards-0.1.0.dist-info/top_level.txt
pyadaptivecards-0.1.0.dist-info/RECORD
