Metadata-Version: 2.1
Name: pyadaptivecards
Version: 0.1.0
Summary: Author adaptive cards in pure python
Home-page: https://github.com/CiscoSE/pyadaptivecards
Author: Marcel Neidinger
Author-email: mneiding@cisco.com
License: Cisco Sample Code License, Version 1.1
Keywords: pyadaptivecards
Platform: UNKNOWN
Classifier: Development Status :: 2 - Pre-Alpha
Classifier: Intended Audience :: Developers
Classifier: Natural Language :: English
Classifier: Programming Language :: Python :: 2
Classifier: Programming Language :: Python :: 2.7
Classifier: Programming Language :: Python :: 3
Classifier: Programming Language :: Python :: 3.4
Classifier: Programming Language :: Python :: 3.5
Classifier: Programming Language :: Python :: 3.6
Classifier: Programming Language :: Python :: 3.7
